ekans/__init__.py
ekans/__main__.py
ekans/checks.py
ekans/commands.py
ekans/entities.py
ekans/errors.py
ekans-0.2.1.dist-info/entry_points.txt
ekans-0.2.1.dist-info/LICENSE
ekans-0.2.1.dist-info/WHEEL
ekans-0.2.1.dist-info/METADATA
ekans-0.2.1.dist-info/RECORD
