Metadata-Version: 2.1
Name: ekans
Version: 0.2.1
Summary: A simple utility to check Conda environments integrity
Home-page: https://git.sr.ht/~diego/ekans
License: MIT
Keywords: conda,environment,checker
Author: Diego Vicente
Author-email: mail@diego.codes
Requires-Python: >=3.8,<4.0
Classifier: License :: OSI Approved :: MIT License
Classifier: Programming Language :: Python :: 3
Classifier: Programming Language :: Python :: 3.8
Classifier: Topic :: Software Development
Requires-Dist: click (>=7.1.1,<8.0.0)
Requires-Dist: packaging (>=20.3,<21.0)
Requires-Dist: pyyaml (>=5.3.1,<6.0.0)
